optlib/__init__.py
optlib/__main__.py
optlib/common.py
optlib/difff.py
optlib/greeks.py
optlib/impvol.py
optlib/mc.py
optlib/old_price.py
optlib/option.py
optlib/prices.py
Optlib-0.3.0.dist-info/WHEEL
Optlib-0.3.0.dist-info/METADATA
Optlib-0.3.0.dist-info/RECORD
