Metadata-Version: 2.1
Name: Optlib
Version: 0.3.0
Summary: Option Lib
License: MIT
Author-email: Nasy <nasyxx+python@gmail.com>
Requires-Python: >=3.9,<3.11
Requires-Dist: chaospy
Requires-Dist: matplotlib>=3.5.2
Requires-Dist: numpy
Requires-Dist: pandas>=1.4.3
Requires-Dist: rich>=12.5.1
Requires-Dist: scipy>=1.8.0
Requires-Dist: setuptools>=63.1.0
